astrometry_extension.cpython-312-x86_64-linux-musl.so
astrometry/series.py
astrometry/__init__.py
astrometry/astrometry_extension_types.pyi
astrometry-4.3.0.dist-info/LICENSE
astrometry-4.3.0.dist-info/WHEEL
astrometry-4.3.0.dist-info/METADATA
astrometry-4.3.0.dist-info/top_level.txt
astrometry-4.3.0.dist-info/RECORD
