Metadata-Version: 2.2
Name: astrometry
Version: 4.3.0
Summary: Astrometry.net solver interface
Author-email: Alexandre Marcireau <alexandre.marcireau@gmail.com>
License:                     GNU GENERAL PUBLIC LICENSE
Project-URL: homepage, https://github.com/neuromorphicsystems/astrometry/
Project-URL: repository, https://github.com/neuromorphicsystems/astrometry/
Project-URL: documentation, https://github.com/neuromorphicsystems/astrometry/
Requires-Python: >=3.9
License-File: LICENSE
Requires-Dist: requests>=1.26
Provides-Extra: astropy
Requires-Dist: astropy>=5; extra == "astropy"
Provides-Extra: lint
Requires-Dist: isort; extra == "lint"
Requires-Dist: black; extra == "lint"
Requires-Dist: pyright; extra == "lint"
Provides-Extra: plot
Requires-Dist: numpy>=1.26; extra == "plot"
Provides-Extra: tests
Requires-Dist: astropy>=5; extra == "tests"
Requires-Dist: psutil==6.1.1; extra == "tests"
Requires-Dist: numpy>=1.26; extra == "tests"
